pingzeex.py
pingzeex-0.0.4.dist-info/LICENSE
pingzeex-0.0.4.dist-info/METADATA
pingzeex-0.0.4.dist-info/WHEEL
pingzeex-0.0.4.dist-info/top_level.txt
pingzeex-0.0.4.dist-info/RECORD
