Metadata-Version: 2.1
Name: pingzeex
Version: 0.0.4
Summary: Pingzeex Python Library
Home-page: https://github.com/nishgaba-ai/pingzeex
Author: Nishchal Gaba
Author-email: nishgaba.ai@gmail.com
License: UNKNOWN
Platform: UNKNOWN
Classifier: Programming Language :: Python :: 3
Classifier: Programming Language :: Python :: 3.6
Classifier: Programming Language :: Python :: 3.7
Classifier: License :: OSI Approved :: MIT License
Classifier: Operating System :: OS Independent
